{
    "default": {
        "separator": ":",
        "attornator": "",
        "props": {
            "telephone": {
                "regex": "phone",
                "type": "string",
                "optional": false,
                "keep": true
            },
            "fid": {
                "regex": "phone",
                "type": "number",
                "optional": false,
                "keep": true
            },
            "name": {
                "regex": "whole",
                "type": "string",
                "optional": true,
                "keep": true
            },
            "surname": {
                "regex": "whole",
                "type": "string",
                "optional": true,
                "keep": true
            },
            "sex": {
                "regex": "whole",
                "type": "string",
                "optional": true,
                "keep": true
            },
            "birthPlace": {
                "regex": "whole",
                "type": "string",
                "optional": true,
                "keep": true
            },
            "residence": {
                "regex": "whole",
                "type": "string",
                "optional": true,
                "keep": true
            },
            "maritalStatus": {
                "regex": "whole",
                "type": "string",
                "optional": true,
                "keep": true
            },
            "profession": {
                "regex": "whole",
                "type": "string",
                "optional": true,
                "keep": true
            },
            "unusefulDate": {
                "regex": "datetime",
                "type": "datetime",
                "optional": true,
                "keep": false
            },
            "email": {
                "regex": "whole",
                "type": "string",
                "optional": true,
                "keep": true
            },
            "birthDate": {
                "regex": "date",
                "type": "date",
                "optional": true,
                "keep": true
            }
        }
    },
    "AFG": {
        "separator": ":",
        "attornator": "",
        "props": {
            "telephone": {
                "regex": "phone",
                "type": "string",
                "optional": false,
                "keep": true
            },
            "fid": {
                "regex": "numeric",
                "type": "number",
                "optional": false,
                "keep": true
            },
            "name": {
                "regex": "whole",
                "type": "string",
                "optional": true,
                "keep": true
            },
            "surname": {
                "regex": "whole",
                "type": "string",
                "optional": true,
                "keep": true
            },
            "sex": {
                "regex": "whole",
                "type": "string",
                "optional": true,
                "keep": true
            },
            "birthPlace": {
                "regex": "whole",
                "type": "string",
                "optional": true,
                "keep": true
            },
            "residence": {
                "regex": "whole",
                "type": "string",
                "optional": true,
                "keep": true
            },
            "maritalStatus": {
                "regex": "whole",
                "type": "string",
                "optional": true,
                "keep": true
            },
            "profession": {
                "regex": "whole",
                "type": "string",
                "optional": true,
                "keep": true
            },
            "unusefulDate": {
                "regex": "whole",
                "type": "string",
                "optional": true,
                "keep": false
            },
            "email": {
                "regex": "whole",
                "type": "string",
                "optional": true,
                "keep": true
            },
            "birthDate": {
                "regex": "date",
                "type": "date",
                "optional": true,
                "keep": true
            },
            "x0": {
                "regex": "whole",
                "type": "string",
                "optional": true,
                "keep": false
            },
            "x1": {
                "regex": "whole",
                "type": "string",
                "optional": true,
                "keep": false
            },
            "x2": {
                "regex": "whole",
                "type": "string",
                "optional": true,
                "keep": false
            },
            "x3": {
                "regex": "whole",
                "type": "string",
                "optional": true,
                "keep": false
            },
            "x4": {
                "regex": "whole",
                "type": "string",
                "optional": true,
                "keep": false
            }
        }
    },
    "AUS": {
        "separator": ":",
        "attornator": "",
        "props": {
            "telephone": {
                "regex": "phone",
                "type": "string",
                "optional": false,
                "keep": true
            },
            "fid": {
                "regex": "numeric",
                "type": "number",
                "optional": false,
                "keep": true
            },
            "name": {
                "regex": "whole",
                "type": "string",
                "optional": true,
                "keep": true
            },
            "surname": {
                "regex": "whole",
                "type": "string",
                "optional": true,
                "keep": true
            },
            "sex": {
                "regex": "whole",
                "type": "string",
                "optional": true,
                "keep": true
            },
            "birthPlace": {
                "regex": "whole",
                "type": "string",
                "optional": true,
                "keep": true
            },
            "residence": {
                "regex": "whole",
                "type": "string",
                "optional": true,
                "keep": true
            },
            "maritalStatus": {
                "regex": "whole",
                "type": "string",
                "optional": true,
                "keep": true
            },
            "profession": {
                "regex": "whole",
                "type": "string",
                "optional": true,
                "keep": true
            },
            "unusefulDate": {
                "regex": "whole",
                "type": "string",
                "optional": true,
                "keep": true
            },
            "email": {
                "regex": "whole",
                "type": "string",
                "optional": true,
                "keep": true
            },
            "birthDate": {
                "regex": "date",
                "type": "date",
                "optional": true,
                "keep": true
            }
        }
    },
    "BHR": {
        "separator": ",",
        "attornator": "",
        "props": {
            "fid": {
                "regex": "numeric",
                "type": "number",
                "optional": false,
                "keep": true
            },
            "telephone": {
                "regex": "phone",
                "type": "string",
                "optional": false,
                "keep": true
            },
            "name": {
                "regex": "whole_comma",
                "type": "string",
                "optional": true,
                "keep": true
            },
            "surname": {
                "regex": "whole_comma",
                "type": "string",
                "optional": true,
                "keep": true
            },
            "email": {
                "regex": "whole_comma",
                "type": "string",
                "optional": true,
                "keep": true
            },
            "birthDate": {
                "regex": "whole_comma",
                "type": "string",
                "optional": true,
                "keep": true
            },
            "sex": {
                "regex": "whole_comma",
                "type": "string",
                "optional": true,
                "keep": true
            },
            "language": {
                "regex": "whole_comma",
                "type": "string",
                "optional": true,
                "keep": true
            },
            "residence": {
                "regex": "whole_comma",
                "type": "string",
                "optional": true,
                "keep": true
            },
            "location1": {
                "regex": "whole_comma",
                "type": "string",
                "optional": true,
                "keep": true
            },
            "location2": {
                "regex": "whole_comma",
                "type": "string",
                "optional": true,
                "keep": true
            },
            "link": {
                "regex": "whole_comma",
                "type": "string",
                "optional": true,
                "keep": true
            },
            "fbLink1": {
                "regex": "whole_comma",
                "type": "string",
                "optional": true,
                "keep": true
            },
            "fbLink2": {
                "regex": "whole_comma",
                "type": "string",
                "optional": true,
                "keep": true
            },
            "fbLink3": {
                "regex": "whole_comma",
                "type": "string",
                "optional": true,
                "keep": true
            },
            "fbLink4": {
                "regex": "whole_comma",
                "type": "string",
                "optional": true,
                "keep": true
            },
            "fbLink5": {
                "regex": "whole_comma",
                "type": "string",
                "optional": true,
                "keep": true
            },
            "fbLink6": {
                "regex": "whole_comma",
                "type": "string",
                "optional": true,
                "keep": true
            },
            "fbLink7": {
                "regex": "whole_comma",
                "type": "string",
                "optional": true,
                "keep": true
            },
            "fbLink8": {
                "regex": "whole_comma",
                "type": "string",
                "optional": true,
                "keep": true
            },
            "fbLink9": {
                "regex": "whole_comma",
                "type": "string",
                "optional": true,
                "keep": true
            },
            "fbLink10": {
                "regex": "whole_comma",
                "type": "string",
                "optional": true,
                "keep": true
            },
            "fbLink11": {
                "regex": "whole_comma",
                "type": "string",
                "optional": true,
                "keep": true
            },
            "fbLink12": {
                "regex": "whole_comma",
                "type": "string",
                "optional": true,
                "keep": true
            }
        }
    },
    "DNK": {
        "separator": ":",
        "attornator": "",
        "props": {
            "telephone": {
                "regex": "phone",
                "type": "string",
                "optional": false,
                "keep": true
            },
            "fid": {
                "regex": "numeric",
                "type": "number",
                "optional": false,
                "keep": true
            },
            "name": {
                "regex": "whole",
                "type": "string",
                "optional": true,
                "keep": true
            },
            "surname": {
                "regex": "whole",
                "type": "string",
                "optional": true,
                "keep": true
            },
            "sex": {
                "regex": "whole",
                "type": "string",
                "optional": true,
                "keep": true
            },
            "birthPlace": {
                "regex": "whole",
                "type": "string",
                "optional": true,
                "keep": true
            },
            "residence": {
                "regex": "whole",
                "type": "string",
                "optional": true,
                "keep": true
            },
            "maritalStatus": {
                "regex": "whole",
                "type": "string",
                "optional": true,
                "keep": true
            },
            "profession": {
                "regex": "whole",
                "type": "string",
                "optional": true,
                "keep": true
            },
            "unknownDate": {
                "regex": "whole",
                "type": "string",
                "optional": true,
                "keep": false
            },
            "email": {
                "regex": "whole",
                "type": "string",
                "optional": true,
                "keep": true
            },
            "birthDate": {
                "regex": "whole",
                "type": "date",
                "optional": true,
                "keep": true
            }
        }
    },
    "DZA": {
        "separator": ",",
        "attornator": "",
        "props": {
            "fid": {
                "regex": "numeric",
                "type": "number",
                "optional": false,
                "keep": true
            },
            "telephone": {
                "regex": "phone",
                "type": "string",
                "optional": false,
                "keep": true
            },
            "name": {
                "regex": "whole_comma",
                "type": "string",
                "optional": true,
                "keep": true
            },
            "surname": {
                "regex": "whole_comma",
                "type": "string",
                "optional": true,
                "keep": true
            },
            "email": {
                "regex": "whole_comma",
                "type": "string",
                "optional": true,
                "keep": true
            },
            "birthDate": {
                "regex": "whole_comma",
                "type": "string",
                "optional": true,
                "keep": true
            },
            "sex": {
                "regex": "whole_comma",
                "type": "string",
                "optional": true,
                "keep": true
            },
            "language": {
                "regex": "whole_comma",
                "type": "string",
                "optional": true,
                "keep": true
            },
            "residence": {
                "regex": "whole_comma",
                "type": "string",
                "optional": true,
                "keep": true
            },
            "location1": {
                "regex": "whole_comma",
                "type": "string",
                "optional": true,
                "keep": true
            },
            "location2": {
                "regex": "whole_comma",
                "type": "string",
                "optional": true,
                "keep": true
            },
            "link": {
                "regex": "whole_comma",
                "type": "string",
                "optional": true,
                "keep": true
            },
            "fbLink1": {
                "regex": "whole_comma",
                "type": "string",
                "optional": true,
                "keep": true
            },
            "fbLink2": {
                "regex": "whole_comma",
                "type": "string",
                "optional": true,
                "keep": true
            },
            "fbLink3": {
                "regex": "whole_comma",
                "type": "string",
                "optional": true,
                "keep": true
            },
            "fbLink4": {
                "regex": "whole_comma",
                "type": "string",
                "optional": true,
                "keep": true
            },
            "fbLink5": {
                "regex": "whole_comma",
                "type": "string",
                "optional": true,
                "keep": true
            },
            "fbLink6": {
                "regex": "whole_comma",
                "type": "string",
                "optional": true,
                "keep": true
            },
            "fbLink7": {
                "regex": "whole_comma",
                "type": "string",
                "optional": true,
                "keep": true
            },
            "fbLink8": {
                "regex": "whole_comma",
                "type": "string",
                "optional": true,
                "keep": true
            },
            "fbLink9": {
                "regex": "whole_comma",
                "type": "string",
                "optional": true,
                "keep": true
            },
            "fbLink10": {
                "regex": "whole_comma",
                "type": "string",
                "optional": true,
                "keep": true
            },
            "fbLink11": {
                "regex": "whole_comma",
                "type": "string",
                "optional": true,
                "keep": true
            },
            "fbLink12": {
                "regex": "whole_comma",
                "type": "string",
                "optional": true,
                "keep": true
            }
        }
    },
    "DEU": {
        "separator": ",",
        "attornator": "",
        "props": {
            "telephone": {
                "regex": "phone",
                "type": "string",
                "optional": false,
                "keep": true
            },
            "fid": {
                "regex": "numeric",
                "type": "number",
                "optional": false,
                "keep": true
            },
            "name": {
                "regex": "whole_comma",
                "type": "string",
                "optional": true,
                "keep": true
            },
            "surname": {
                "regex": "whole_comma",
                "type": "string",
                "optional": true,
                "keep": true
            },
            "sex": {
                "regex": "whole_comma",
                "type": "string",
                "optional": true,
                "keep": true
            },
            "birthPlace": {
                "regex": "place_comma",
                "type": "string",
                "optional": true,
                "keep": true
            },
            "residence": {
                "regex": "place_comma",
                "type": "string",
                "optional": true,
                "keep": true
            },
            "maritalStatus": {
                "regex": "whole_comma",
                "type": "string",
                "optional": true,
                "keep": true
            },
            "profession": {
                "regex": "total_whole",
                "type": "string",
                "optional": true,
                "keep": true
            },
            "unusefulDate": {
                "regex": "datetime_de",
                "type": "datetime",
                "optional": true,
                "keep": false
            },
            "x": {
                "regex": "whole_comma",
                "type": "string",
                "optional": true,
                "keep": true
            },
            "y": {
                "regex": "whole_comma",
                "type": "string",
                "optional": true,
                "keep": true
            }
        }
    },
    "EGY": {
        "separator": ",",
        "attornator": "\"",
        "props": {
            "fid": {
                "regex": "numeric",
                "type": "number",
                "optional": false,
                "keep": true
            },
            "x1": {
                "regex": "whole_comma",
                "type": "string",
                "optional": true,
                "keep": false
            },
            "email": {
                "regex": "whole_comma",
                "type": "string",
                "optional": true,
                "keep": true
            },
            "telephone": {
                "regex": "phone",
                "type": "string",
                "optional": false,
                "keep": true
            },
            "x3": {
                "regex": "whole_comma",
                "type": "string",
                "optional": true,
                "keep": false
            },
            "birthDate": {
                "regex": "date",
                "type": "date",
                "optional": true,
                "keep": true
            },
            "name": {
                "regex": "whole_comma",
                "type": "string",
                "optional": true,
                "keep": true
            },
            "surname": {
                "regex": "whole_comma",
                "type": "string",
                "optional": true,
                "keep": true
            },
            "sex": {
                "regex": "whole_comma",
                "type": "string",
                "optional": true,
                "keep": true
            },
            "fbLink": {
                "regex": "whole_comma",
                "type": "string",
                "optional": true,
                "keep": true
            },
            "x9": {
                "regex": "whole_comma",
                "type": "string",
                "optional": true,
                "keep": false
            },
            "x10": {
                "regex": "whole_comma",
                "type": "string",
                "optional": true,
                "keep": false
            },
            "fullname": {
                "regex": "whole_comma",
                "type": "string",
                "optional": true,
                "keep": true
            },
            "x12": {
                "regex": "whole_comma",
                "type": "string",
                "optional": true,
                "keep": false
            },
            "profession": {
                "regex": "whole_comma",
                "type": "string",
                "optional": true,
                "keep": true
            },
            "x14": {
                "regex": "whole_comma",
                "type": "string",
                "optional": true,
                "keep": false
            },
            "birthPlace": {
                "regex": "whole_comma",
                "type": "string",
                "optional": true,
                "keep": true
            },
            "residence": {
                "regex": "whole_comma",
                "type": "string",
                "optional": true,
                "keep": true
            },
            "x17": {
                "regex": "whole_comma",
                "type": "string",
                "optional": true,
                "keep": false
            },
            "fbEmail": {
                "regex": "whole_comma",
                "type": "string",
                "optional": true,
                "keep": true
            },
            "x19": {
                "regex": "whole_comma",
                "type": "string",
                "optional": true,
                "keep": false
            },
            "x20": {
                "regex": "whole_comma",
                "type": "string",
                "optional": true,
                "keep": false
            },
            "x21": {
                "regex": "whole_comma",
                "type": "string",
                "optional": true,
                "keep": false
            },
            "unknownDate1": {
                "regex": "datetime",
                "type": "datetime",
                "optional": true,
                "keep": false
            },
            "unknownDate2": {
                "regex": "whole_comma",
                "type": "datetime",
                "optional": true,
                "keep": false
            },
            "x24": {
                "regex": "whole_comma",
                "type": "string",
                "optional": true,
                "keep": false
            },
            "x25": {
                "regex": "whole_comma",
                "type": "string",
                "optional": true,
                "keep": false
            },
            "x26": {
                "regex": "whole_comma",
                "type": "string",
                "optional": true,
                "keep": false
            },
            "x27": {
                "regex": "whole_comma",
                "type": "string",
                "optional": true,
                "keep": false
            },
            "x28": {
                "regex": "whole_comma",
                "type": "string",
                "optional": true,
                "keep": false
            },
            "x29": {
                "regex": "whole_comma",
                "type": "string",
                "optional": true,
                "keep": false
            },
            "x30": {
                "regex": "whole_comma",
                "type": "string",
                "optional": true,
                "keep": false
            },
            "x31": {
                "regex": "whole_comma",
                "type": "string",
                "optional": true,
                "keep": false
            },
            "x32": {
                "regex": "whole_comma",
                "type": "string",
                "optional": true,
                "keep": false
            },
            "x33": {
                "regex": "whole_comma",
                "type": "string",
                "optional": true,
                "keep": false
            }
        }
    }
}